
    [
        {
         "Installment No.": 1,
         "Stage Number": 1,
         "Installment Due Date": "10-Jul-22",
         "Installment Amount": 4754.420694549735,
         "Interest Rate": 0.12,
         "Component 1 (Principal)": 3758.2563109880916,
         "Component 2 (Interest)": 996.1643835616438,
         "Component 3 (Fees)": 0,
         "Component 4 (Insurance Premium)": 0,
         "Opening Balance": "$1,01,000.00",
         "Closing Balance": 97241.74368901191
        },
        {
         "Installment No.": 2,
         "Stage Number": 1,
         "Installment Due Date": "10-Aug-22",
         "Installment Amount": 4754.420694549735,
         "Interest Rate": 0.12,
         "Component 1 (Principal)": 3763.354156130217,
         "Component 2 (Interest)": 991.0665384195187,
         "Component 3 (Fees)": 0,
         "Component 4 (Insurance Premium)": 0,
         "Opening Balance": 97241.74368901191,
         "Closing Balance": 93478.3895328817
        },
        {
         "Installment No.": 3,
         "Stage Number": 1,
         "Installment Due Date": "10-Sep-22",
         "Installment Amount": 4754.420694549735,
         "Interest Rate": 0.12,
         "Component 1 (Principal)": 3801.7094368447492,
         "Component 2 (Interest)": 952.7112577049861,
         "Component 3 (Fees)": 0,
         "Component 4 (Insurance Premium)": 0,
         "Opening Balance": 93478.3895328817,
         "Closing Balance": 89676.68009603696
        },
        {
         "Installment No.": 4,
         "Stage Number": 1,
         "Installment Due Date": "10-Oct-22",
         "Installment Amount": 4754.420694549735,
         "Interest Rate": 0.12,
         "Component 1 (Principal)": 3869.9383703148505,
         "Component 2 (Interest)": 884.482324234885,
         "Component 3 (Fees)": 0,
         "Component 4 (Insurance Premium)": 0,
         "Opening Balance": 89676.68009603696,
         "Closing Balance": 85806.74172572211
        },
        {
         "Installment No.": 5,
         "Stage Number": 1,
         "Installment Due Date": "10-Nov-22",
         "Installment Amount": 4754.420694549735,
         "Interest Rate": 0.12,
         "Component 1 (Principal)": 3879.897189838266,
         "Component 2 (Interest)": 874.5235047114691,
         "Component 3 (Fees)": 0,
         "Component 4 (Insurance Premium)": 0,
         "Opening Balance": 85806.74172572211,
         "Closing Balance": 81926.84453588384
        },
        {
         "Installment No.": 6,
         "Stage Number": 1,
         "Installment Due Date": "10-Dec-22",
         "Installment Amount": 4754.420694549735,
         "Interest Rate": 0.12,
         "Component 1 (Principal)": 3946.3751046067714,
         "Component 2 (Interest)": 808.0455899429638,
         "Component 3 (Fees)": 0,
         "Component 4 (Insurance Premium)": 0,
         "Opening Balance": 81926.84453588384,
         "Closing Balance": 77980.46943127706
        },
        {
         "Installment No.": 7,
         "Stage Number": 1,
         "Installment Due Date": "10-Jan-23",
         "Installment Amount": 4754.420694549735,
         "Interest Rate": 0.12,
         "Component 1 (Principal)": 3959.6608417158977,
         "Component 2 (Interest)": 794.7598528338375,
         "Component 3 (Fees)": 0,
         "Component 4 (Insurance Premium)": 0,
         "Opening Balance": 77980.46943127706,
         "Closing Balance": 74020.80858956116
        },
        {
         "Installment No.": 8,
         "Stage Number": 1,
         "Installment Due Date": "10-Feb-23",
         "Installment Amount": 4754.420694549735,
         "Interest Rate": 0.12,
         "Component 1 (Principal)": 4000.0168371437967,
         "Component 2 (Interest)": 754.4038574059384,
         "Component 3 (Fees)": 0,
         "Component 4 (Insurance Premium)": 0,
         "Opening Balance": 74020.80858956116,
         "Closing Balance": 70020.79175241737
        },
        {
         "Installment No.": 9,
         "Stage Number": 1,
         "Installment Due Date": "10-Mar-23",
         "Installment Amount": 4754.420694549735,
         "Interest Rate": 0.12,
         "Component 1 (Principal)": 4109.84573485625,
         "Component 2 (Interest)": 644.5749596934859,
         "Component 3 (Fees)": 0,
         "Component 4 (Insurance Premium)": 0,
         "Opening Balance": 70020.79175241737,
         "Closing Balance": 65910.94601756112
        },
        {
         "Installment No.": 10,
         "Stage Number": 1,
         "Installment Due Date": "10-Apr-23",
         "Installment Amount": 4754.420694549735,
         "Interest Rate": 0.12,
         "Component 1 (Principal)": 4082.670778973496,
         "Component 2 (Interest)": 671.7499155762392,
         "Component 3 (Fees)": 0,
         "Component 4 (Insurance Premium)": 0,
         "Opening Balance": 65910.94601756112,
         "Closing Balance": 61828.27523858762
        },
        {
         "Installment No.": 11,
         "Stage Number": 1,
         "Installment Due Date": "10-May-23",
         "Installment Amount": 4754.420694549735,
         "Interest Rate": 0.12,
         "Component 1 (Principal)": 4144.607568908871,
         "Component 2 (Interest)": 609.8131256408643,
         "Component 3 (Fees)": 0,
         "Component 4 (Insurance Premium)": 0,
         "Opening Balance": 61828.27523858762,
         "Closing Balance": 57683.667669678754
        },
        {
         "Installment No.": 12,
         "Stage Number": 1,
         "Installment Due Date": "10-Jun-23",
         "Installment Amount": 4754.420694549735,
         "Interest Rate": 0.12,
         "Component 1 (Principal)": 4166.521396656023,
         "Component 2 (Interest)": 587.8992978937122,
         "Component 3 (Fees)": 0,
         "Component 4 (Insurance Premium)": 0,
         "Opening Balance": 57683.667669678754,
         "Closing Balance": 53517.14627302273
        },
        {
         "Installment No.": 13,
         "Stage Number": 1,
         "Installment Due Date": "10-Jul-23",
         "Installment Amount": 4754.420694549735,
         "Interest Rate": 0.12,
         "Component 1 (Principal)": 4226.580347747319,
         "Component 2 (Interest)": 527.840346802416,
         "Component 3 (Fees)": 0,
         "Component 4 (Insurance Premium)": 0,
         "Opening Balance": 53517.14627302273,
         "Closing Balance": 49290.56592527541
        },
        {
         "Installment No.": 14,
         "Stage Number": 1,
         "Installment Due Date": "10-Aug-23",
         "Installment Amount": 4754.420694549735,
         "Interest Rate": 0.12,
         "Component 1 (Principal)": 4252.062050051038,
         "Component 2 (Interest)": 502.3586444986974,
         "Component 3 (Fees)": 0,
         "Component 4 (Insurance Premium)": 0,
         "Opening Balance": 49290.56592527541,
         "Closing Balance": 45038.50387522437
        },
        {
         "Installment No.": 15,
         "Stage Number": 1,
         "Installment Due Date": "10-Sep-23",
         "Installment Amount": 4754.420694549735,
         "Interest Rate": 0.12,
         "Component 1 (Principal)": 4295.398134506353,
         "Component 2 (Interest)": 459.0225600433826,
         "Component 3 (Fees)": 0,
         "Component 4 (Insurance Premium)": 0,
         "Opening Balance": 45038.50387522437,
         "Closing Balance": 40743.10574071802
        },
        {
         "Installment No.": 16,
         "Stage Number": 1,
         "Installment Due Date": "10-Oct-23",
         "Installment Amount": 4754.420694549735,
         "Interest Rate": 0.12,
         "Component 1 (Principal)": 4352.570884504297,
         "Component 2 (Interest)": 401.849810045438,
         "Component 3 (Fees)": 0,
         "Component 4 (Insurance Premium)": 0,
         "Opening Balance": 40743.10574071802,
         "Closing Balance": 36390.53485621372
        },
        {
         "Installment No.": 17,
         "Stage Number": 1,
         "Installment Due Date": "10-Nov-23",
         "Installment Amount": 4754.420694549735,
         "Interest Rate": 0.12,
         "Component 1 (Principal)": 4383.536339302845,
         "Component 2 (Interest)": 370.8843552468905,
         "Component 3 (Fees)": 0,
         "Component 4 (Insurance Premium)": 0,
         "Opening Balance": 36390.53485621372,
         "Closing Balance": 32006.998516910877
        },
        {
         "Installment No.": 18,
         "Stage Number": 1,
         "Installment Due Date": "10-Dec-23",
         "Installment Amount": 4754.420694549735,
         "Interest Rate": 0.12,
         "Component 1 (Principal)": 4438.735229725409,
         "Component 2 (Interest)": 315.68546482432646,
         "Component 3 (Fees)": 0,
         "Component 4 (Insurance Premium)": 0,
         "Opening Balance": 32006.998516910877,
         "Closing Balance": 27568.263287185466
        },
        {
         "Installment No.": 19,
         "Stage Number": 1,
         "Installment Due Date": "10-Jan-24",
         "Installment Amount": 4754.420694549735,
         "Interest Rate": 0.12,
         "Component 1 (Principal)": 4473.450997485817,
         "Component 2 (Interest)": 280.9696970639176,
         "Component 3 (Fees)": 0,
         "Component 4 (Insurance Premium)": 0,
         "Opening Balance": 27568.263287185466,
         "Closing Balance": 23094.81228969965
        },
        {
         "Installment No.": 20,
         "Stage Number": 1,
         "Installment Due Date": "10-Feb-24",
         "Installment Amount": 4754.420694549735,
         "Interest Rate": 0.12,
         "Component 1 (Principal)": 4519.043429569782,
         "Component 2 (Interest)": 235.37726497995257,
         "Component 3 (Fees)": 0,
         "Component 4 (Insurance Premium)": 0,
         "Opening Balance": 23094.81228969965,
         "Closing Balance": 18575.76886012987
        },
        {
         "Installment No.": 21,
         "Stage Number": 1,
         "Installment Due Date": "10-Mar-24",
         "Installment Amount": 4754.420694549735,
         "Interest Rate": 0.12,
         "Component 1 (Principal)": 4577.314733910689,
         "Component 2 (Interest)": 177.10596063904643,
         "Component 3 (Fees)": 0,
         "Component 4 (Insurance Premium)": 0,
         "Opening Balance": 18575.76886012987,
         "Closing Balance": 13998.45412621918
        },
        {
         "Installment No.": 22,
         "Stage Number": 1,
         "Installment Due Date": "10-Apr-24",
         "Installment Amount": 4754.420694549735,
         "Interest Rate": 0.12,
         "Component 1 (Principal)": 4611.751518249638,
         "Component 2 (Interest)": 142.66917630009684,
         "Component 3 (Fees)": 0,
         "Component 4 (Insurance Premium)": 0,
         "Opening Balance": 13998.45412621918,
         "Closing Balance": 9386.702607969542
        },
        {
         "Installment No.": 23,
         "Stage Number": 1,
         "Installment Due Date": "10-May-24",
         "Installment Amount": 4754.420694549735,
         "Interest Rate": 0.12,
         "Component 1 (Principal)": 4661.839518142365,
         "Component 2 (Interest)": 92.58117640737082,
         "Component 3 (Fees)": 0,
         "Component 4 (Insurance Premium)": 0,
         "Opening Balance": 9386.702607969542,
         "Closing Balance": 4724.863089827178
        },
        {
         "Installment No.": 24,
         "Stage Number": 1,
         "Installment Due Date": "10-Jun-24",
         "Installment Amount": 4773.017858852266,
         "Interest Rate": 0.12,
         "Component 1 (Principal)": 4724.863089827178,
         "Component 2 (Interest)": 48.154769025087944,
         "Component 3 (Fees)": 0,
         "Component 4 (Insurance Premium)": 0,
         "Opening Balance": 4724.863089827178,
         "Closing Balance": 0
        }
       ]
